tushare_etl/__init__.py
tushare_etl-0.1.0.dist-info/METADATA
tushare_etl-0.1.0.dist-info/WHEEL
tushare_etl-0.1.0.dist-info/RECORD
